django_notify/__init__.py
django_notify/admin.py
django_notify/decorators.py
django_notify/models.py
django_notify/settings.py
django_notify/tests.py
django_notify/urls.py
django_notify/views.py
django_notify/migrations/0001_initial.py
django_notify/migrations/__init__.py
wiki/__init__.py
wiki/admin.py
wiki/apps.py
wiki/decorators.py
wiki/forms.py
wiki/managers.py
wiki/middleware.py
wiki/tests.py
wiki/urls.py
wiki/conf/__init__.py
wiki/conf/settings.py
wiki/core/__init__.py
wiki/core/compat.py
wiki/core/diff.py
wiki/core/exceptions.py
wiki/core/extensions.py
wiki/core/http.py
wiki/core/permissions.py
wiki/core/processors.py
wiki/core/plugins/__init__.py
wiki/core/plugins/base.py
wiki/core/plugins/loader.py
wiki/core/plugins/registry.py
wiki/editors/__init__.py
wiki/editors/base.py
wiki/editors/markitup.py
wiki/management/__init__.py
wiki/management/commands/__init__.py
wiki/management/commands/wikiviz.py
wiki/migrations/0001_initial.py
wiki/migrations/0002_remove_article_subscription.py
wiki/migrations/0003_ip_address_conv.py
wiki/migrations/0004_increase_slug_size.py
wiki/migrations/0005_remove_attachments_and_images.py
wiki/migrations/0006_auto_20200110_1003.py
wiki/migrations/0007_alter_articleforobject_content_type.py
wiki/migrations/__init__.py
wiki/models/__init__.py
wiki/models/article.py
wiki/models/pluginbase.py
wiki/models/urlpath.py
wiki/plugins/__init__.py
wiki/plugins/attachments/__init__.py
wiki/plugins/attachments/admin.py
wiki/plugins/attachments/forms.py
wiki/plugins/attachments/markdown_extensions.py
wiki/plugins/attachments/models.py
wiki/plugins/attachments/settings.py
wiki/plugins/attachments/views.py
wiki/plugins/attachments/wiki_plugin.py
wiki/plugins/attachments/migrations/0001_initial.py
wiki/plugins/attachments/migrations/__init__.py
wiki/plugins/attachments/templates/wiki/plugins/attachments/delete.html
wiki/plugins/attachments/templates/wiki/plugins/attachments/history.html
openedx_django_wiki-3.1.1.dist-info/METADATA
openedx_django_wiki-3.1.1.dist-info/WHEEL
openedx_django_wiki-3.1.1.dist-info/top_level.txt
openedx_django_wiki-3.1.1.dist-info/RECORD
