Metadata-Version: 2.4
Name: openedx-django-wiki
Version: 3.1.1
Summary: A wiki system written for the Django framework.
Home-page: https://github.com/openedx/django-wiki
Author: Benjamin Bach
Author-email: benjamin@overtag.dk
License: GPLv3
Keywords: django wiki markdown
Classifier: Development Status :: 2 - Pre-Alpha
Classifier: License :: OSI Approved :: GNU General Public License v3 (GPLv3)
Classifier: Environment :: Web Environment
Classifier: Framework :: Django
Classifier: Intended Audience :: Developers
Classifier: Operating System :: OS Independent
Classifier: Programming Language :: Python :: 3.12
Classifier: Framework :: Django
Classifier: Framework :: Django :: 4.2
Classifier: Framework :: Django :: 5.2
Classifier: Topic :: Internet :: WWW/HTTP :: Dynamic Content
Classifier: Topic :: Software Development
Classifier: Topic :: Software Development :: Libraries :: Application Frameworks
Requires-Dist: bleach[css]>=6.0.0
Requires-Dist: sorl-thumbnail
Requires-Dist: django-sekizai
Requires-Dist: django-mptt
Requires-Dist: Markdown
Requires-Dist: django
Dynamic: author
Dynamic: author-email
Dynamic: classifier
Dynamic: description
Dynamic: description-content-type
Dynamic: home-page
Dynamic: keywords
Dynamic: license
Dynamic: requires-dist
Dynamic: summary
